__init__.py
devtools.py
env.py
initializer.py
venv_helper.py
i3/__init__.py
i3/bar.py
i3/cmd.py
i3/doc.py
i3/for_windows.py
i3/i3_config.py
i3/key.py
i3/mode.py
i3/set.py
i3/wsp.py
install/__init__ .py
install/apt.py
install/dnf.py
install/flatpak.py
install/install.py
install/pacman.py
install/pip.py
install/snap.py
install/system_package_manager.py
install/winget.py
install/yay.py
util/__init__.py
util/config_reader.py
util/github_repo.py
util/os.py
util/util.py
pc_initializer-0.0.1.dist-info/LICENSE
pc_initializer-0.0.1.dist-info/METADATA
pc_initializer-0.0.1.dist-info/WHEEL
pc_initializer-0.0.1.dist-info/entry_points.txt
pc_initializer-0.0.1.dist-info/top_level.txt
pc_initializer-0.0.1.dist-info/RECORD
