Metadata-Version: 2.1
Name: pc-initializer
Version: 0.0.1
Summary: A small example package
Author-email: setre14 <simon.schuster@outlook.com>
Project-URL: Homepage, https://github.com/Setre14/inititializer
Project-URL: Bug Tracker, https://github.com/Setre14/inititializer/issues
Classifier: Programming Language :: Python :: 3
Classifier: License :: OSI Approved :: MIT License
Classifier: Operating System :: OS Independent
Requires-Python: >=3.10
License-File: LICENSE
Requires-Dist: pygithub
Requires-Dist: jproperties
